extractnet/__init__.py
extractnet/blocks.cpp
extractnet/blocks.cpython-38-darwin.so
extractnet/blocks.pyx
extractnet/compat.py
extractnet/lcs.cpp
extractnet/lcs.cpython-38-darwin.so
extractnet/lcs.pyx
extractnet/name_crf.py
extractnet/nn_models.py
extractnet/pipeline.py
extractnet/util.py
extractnet/features/__init__.py
extractnet/features/_kohlschuetter.cpp
extractnet/features/_kohlschuetter.cpython-38-darwin.so
extractnet/features/_kohlschuetter.pyx
extractnet/features/_readability.cc
extractnet/features/_readability.cpp
extractnet/features/_readability.cpython-38-darwin.so
extractnet/features/_readability.pyx
extractnet/features/_weninger.cpp
extractnet/features/_weninger.cpython-38-darwin.so
extractnet/features/_weninger.pyx
extractnet/features/author.py
extractnet/features/css.py
extractnet/features/kohlschuetter.py
extractnet/features/readability.py
extractnet/features/standardized.py
extractnet/features/weninger.py
extractnet/metadata_extraction/constant.py
extractnet/metadata_extraction/json_ld.py
extractnet/metadata_extraction/metadata.py
extractnet/metadata_extraction/metaxpaths.py
extractnet/metadata_extraction/url_utils.py
extractnet/metadata_extraction/utils.py
extractnet/metadata_extraction/video.py
extractnet/models/char_embedding.joblib
extractnet/models/crf.joblib
extractnet/models/news_net.onnx
extractnet/sequence_tagger/__init__.py
extractnet/sequence_tagger/models.py
extractnet-2.0.7.dist-info/LICENSE
extractnet-2.0.7.dist-info/METADATA
extractnet-2.0.7.dist-info/WHEEL
extractnet-2.0.7.dist-info/top_level.txt
extractnet-2.0.7.dist-info/RECORD
