Metadata-Version: 2.1
Name: extractnet
Version: 2.0.7
Summary: Extract the main article content (and optionally comments) from a web page
Home-page: https://github.com/currentsapi/extractnet
Author: Peter
Author-email: sales@currentsapi.services
License: MIT
Keywords: automatic content extraction,web page dechroming,HTML parsing
Platform: Posix; MacOS X
Classifier: License :: OSI Approved :: MIT License
Classifier: Development Status :: 5 - Production/Stable
Classifier: Environment :: Web Environment
Classifier: Intended Audience :: Developers
Classifier: Intended Audience :: Science/Research
Classifier: Topic :: Internet :: WWW/HTTP
Classifier: Topic :: Scientific/Engineering
Classifier: Topic :: Scientific/Engineering :: Artificial Intelligence
Classifier: Intended Audience :: Science/Research
Classifier: Programming Language :: Python :: 3
Classifier: Programming Language :: Python :: 3.5
Classifier: Programming Language :: Python :: 3.6
Classifier: Programming Language :: Python :: 3.7
Classifier: Programming Language :: Python :: 3.8
License-File: LICENSE
Requires-Dist: cchardet (>=2.1.7)
Requires-Dist: beautifulsoup4 (==4.9.3)
Requires-Dist: ftfy (<5.0.0,>=4.1.0)
Requires-Dist: numpy (>=1.19.0)
Requires-Dist: onnxruntime (>=1.9.0)
Requires-Dist: scikit-learn (>=0.22.0)
Requires-Dist: tld (==0.12.6)
Requires-Dist: scipy (>=0.17.0)
Requires-Dist: sklearn-crfsuite (==0.3.6)
Requires-Dist: dateparser (==1.1.0)
Requires-Dist: joblib (>=1.1.0)
Requires-Dist: htmldate (==0.7.2)
